Workbook

Sheet Cover page
D4: 3-statement financial model
G7: Project Name | H7: Primary data mine LTD
G8: Prepared by | H8: Raymond Balogun
G9: Date | H9: 15/04/2024
D11: Containing
D12: Output
D13: Calculations
D14: Input

Sheet Output
A1: Primary Data mine LTD | G1: 2022 | H1: =G1+1 -> 2023 | I1: =H1+1 -> 2024 | J1: =I1+1 -> 2025 | K1: =J1+1 -> 2026 | L1: =K1+1 -> 2027 | M1: =L1+1 -> 2028
A2: 3-statement financial model | G2: 44562 | H2: 44927 | I2: 45292 | J2: 45658 | K2: 46023 | L2: 46388 | M2: 46753
A3: Figures are in Naira | G3: 44926 | H3: 45291 | I3: 45657 | J3: 46022 | K3: 46387 | L3: 46752 | M3: 47118
C4: Income Statement
C5: Revenue | G5: 22885469 | H5: 255878758 | I5: =H5*(1+Calculation!I$6) -> 3.6590662e+08 | J5: =I5*(1+Calculation!J$6) -> 5.415418e+08 | K5: =J5*(1+Calculation!K$6) -> 8.2855896e+08 | L5: =K5*(1+Calculation!L$6) -> 1.3091232e+09 | M5: =L5*(1+Calculation!M$6) -> 2.1338707e+09
C6: Cost of Good sold | G6: -8352601 | H6: -148814107 | I6: =-Calculation!I$9*Output!I5 -> -1.0977199e+08 | J6: =-Calculation!J$9*Output!J5 -> -1.4621629e+08 | K6: =-Calculation!K$9*Output!K5 -> -1.9885415e+08 | L6: =-Calculation!L$9*Output!L5 -> -2.7491586e+08 | M6: =-Calculation!M$9*Output!M5 -> -3.8409673e+08
C7: Gross Profit | G7: =SUM(G5:G6) -> 14532868 | H7: =SUM(H5:H6) -> 107064651 | I7: =SUM(I5:I6) -> 2.5613464e+08 | J7: =SUM(J5:J6) -> 3.9532552e+08 | K7: =SUM(K5:K6) -> 6.2970481e+08 | L7: =SUM(L5:L6) -> 1.0342073e+09 | M7: =SUM(M5:M6) -> 1.749774e+09
C8: Expenses:
C9: Operating Expenses | G9: -1821020 | H9: =-20161222+5636624 -> -14524598 | I9: =-Calculation!I12*Output!I5 -> -7318132.5 | J9: =-Calculation!J12*Output!J5 -> -13538545 | K9: =-Calculation!K12*Output!K5 -> -24856769 | L9: =-Calculation!L12*Output!L5 -> -45819310 | M9: =-Calculation!M12*Output!M5 -> -85354830
C10: Personnel Expenses | G10: -9534769 | H10: -47870680 | I10: =Calculation!I15*Output!I5 -> -68455072 | J10: =Calculation!J15*Output!J5 -> -1.0131351e+08 | K10: =Calculation!K15*Output!K5 -> -1.5500967e+08 | L10: =Calculation!L15*Output!L5 -> -2.4491527e+08 | M10: =Calculation!M15*Output!M5 -> -3.9921189e+08
C11: Other Expenses | G11: 0 | H11: 0 | I11: 0 | J11: 0 | K11: 0 | L11: 0 | M11: 0
C12: EBITDA | G12: =SUM(G7:G11) -> 3177079 | H12: =SUM(H7:H11) -> 44669373 | I12: =SUM(I7:I11) -> 1.8036143e+08 | J12: =SUM(J7:J11) -> 2.8047346e+08 | K12: =SUM(K7:K11) -> 4.4983837e+08 | L12: =SUM(L7:L11) -> 7.4347271e+08 | M12: =SUM(M7:M11) -> 1.2652073e+09
C13: Depreciation & Amortization | G13: =-702079 -> -702079 | H13: =-5636624 -> -5636624 | I13: =Calculation!I19 -> -6638818.4 | J13: =Calculation!J19 -> -14092814 | K13: =Calculation!K19 -> -24271254 | L13: =Calculation!L19 -> -39302418 | M13: =Calculation!M19 -> -62860890
C14: Earnings Before Interest & Tax | G14: =SUM(G12:G13) -> 2475000 | H14: =SUM(H12:H13) -> 39032749 | I14: =SUM(I12:I13) -> 1.7372261e+08 | J14: =SUM(J12:J13) -> 2.6638065e+08 | K14: =SUM(K12:K13) -> 4.2556712e+08 | L14: =SUM(L12:L13) -> 7.0417029e+08 | M14: =SUM(M12:M13) -> 1.2023464e+09
C15: Interest Expense | G15: 0 | H15: 0 | I15: 0 | J15: 0 | K15: 0 | L15: 0 | M15: 0
C16: Profit Before Tax | G16: =SUM(G14:G15) -> 2475000 | H16: =SUM(H14:H15) -> 39032749 | I16: =SUM(I14:I15) -> 1.7372261e+08 | J16: =SUM(J14:J15) -> 2.6638065e+08 | K16: =SUM(K14:K15) -> 4.2556712e+08 | L16: =SUM(L14:L15) -> 7.0417029e+08 | M16: =SUM(M14:M15) -> 1.2023464e+09
C17: Taxation | G17: -124 | H17: 0 | I17: =-input!$G$23*Output!I16 -> -52116784 | J17: =-input!$G$23*Output!J16 -> -79914195 | K17: =-input!$G$23*Output!K16 -> -1.2767014e+08 | L17: =-input!$G$23*Output!L16 -> -2.1125109e+08 | M17: =-input!$G$23*Output!M16 -> -3.6070392e+08
C18: Profit After Tax | G18: =SUM(G16:G17) -> 2474876 | H18: =SUM(H16:H17) -> 39032749 | I18: =SUM(I16:I17) -> 1.2160583e+08 | J18: =SUM(J16:J17) -> 1.8646646e+08 | K18: =SUM(K16:K17) -> 2.9789698e+08 | L18: =SUM(L16:L17) -> 4.929192e+08 | M18: =SUM(M16:M17) -> 8.4164248e+08
C19: Value in $ | G19: =G18/$C$20 -> 2062.3967 | H19: =H18/$C$20 -> 32527.291 | I19: =I18/$C$20 -> 101338.19 | J19: =J18/$C$20 -> 155388.71 | K19: =K18/$C$20 -> 248247.49 | L19: =L18/$C$20 -> 410766 | M19: =M18/$C$20 -> 701368.73
C20: 1200
C22: Dividends | G22: 0 | H22: 0 | I22: 0 | J22: 0 | K22: 0 | L22: 0 | M22: 0
C23: Retained Earnings | G23: =G18-G22 -> 2474876 | H23: =H18-H22 -> 39032749 | I23: =I18-I22 -> 1.2160583e+08 | J23: =J18-J22 -> 1.8646646e+08 | K23: =K18-K22 -> 2.9789698e+08 | L23: =L18-L22 -> 4.929192e+08 | M23: =M18-M22 -> 8.4164248e+08
C24: Retained Earnings BF | G24: 0 | H24: =G25 -> 2474876 | I24: =H25 -> 41507625 | J24: =I25 -> 1.6311345e+08 | K24: =J25 -> 3.4957991e+08 | L24: =K25 -> 6.4747689e+08 | M24: =L25 -> 1.1403961e+09
C25: Retained Earnings CF | G25: =SUM(G23:G24) -> 2474876 | H25: =SUM(H23:H24) -> 41507625 | I25: =SUM(I23:I24) -> 1.6311345e+08 | J25: =SUM(J23:J24) -> 3.4957991e+08 | K25: =SUM(K23:K24) -> 6.4747689e+08 | L25: =SUM(L23:L24) -> 1.1403961e+09 | M25: =SUM(M23:M24) -> 1.9820386e+09
C26: Value in $ | G26: =G25/$C$20 -> 2062.3967 | H26: =H25/$C$20 -> 34589.688 | I26: =I25/$C$20 -> 135927.88 | J26: =J25/$C$20 -> 291316.59 | K26: =K25/$C$20 -> 539564.08 | L26: =L25/$C$20 -> 950330.08 | M26: =M25/$C$20 -> 1651698.8
C27: 1200
C29: Statement of Cashflows
C31: Operating Activities
C32: Profit Before Tax | G32: =G14 -> 2475000 | H32: 39032749 | I32: =I14 -> 1.7372261e+08 | J32: =J14 -> 2.6638065e+08 | K32: =K14 -> 4.2556712e+08 | L32: =L14 -> 7.0417029e+08 | M32: =M14 -> 1.2023464e+09
C33: Add:
C34: Interest Expense | G34: 0 | H34: 0 | I34: 0 | J34: 0 | K34: 0 | L34: 0 | M34: 0
C35: Depreciation | G35: =-G13 -> 702079 | H35: =-H13 -> 5636624 | I35: =-I13 -> 6638818.4 | J35: =-J13 -> 14092814 | K35: =-K13 -> 24271254 | L35: =-L13 -> 39302418 | M35: =-M13 -> 62860890
C36: Changes in Working Capital:
C37: Inventory | G37: 0 | H37: 0 | I37: 0 | J37: 0 | K37: 0 | L37: 0 | M37: 0
C38: Receivables | G38: =-Calculation!G24+Calculation!F24 -> -5689994 | H38: =-Calculation!H24+Calculation!G24 -> -11852701 | I38: =-Calculation!I24+Calculation!H24 -> -4511950.8 | J38: =-Calculation!J24+Calculation!I24 -> -10586230 | K38: =-Calculation!K24+Calculation!J24 -> -17299664 | L38: =-Calculation!L24+Calculation!K24 -> -28965513 | M38: =-Calculation!M24+Calculation!L24 -> -49710814
C39: Payables | G39: 9387929 | H39: 2862169 | I39: =Calculation!I25-Calculation!H25 -> -2325507.4 | J39: =Calculation!J25-Calculation!I25 -> 3294964.1 | K39: =Calculation!K25-Calculation!J25 -> 4759039.7 | L39: =Calculation!L25-Calculation!K25 -> 6876812.4 | M39: =Calculation!M25-Calculation!L25 -> 9871147.3
C40: Tax Paid | G40: =G17 -> -124 | H40: - | I40: =I17 -> -52116784 | J40: =J17 -> -79914195 | K40: =K17 -> -1.2767014e+08 | L40: =L17 -> -2.1125109e+08 | M40: =M17 -> -3.6070392e+08
C41: Net Cash Generated from/(Used) | G41: =SUM(G32:G40) -> 6874890 | H41: =SUM(H32:H40) -> 35678841 | I41: =SUM(I32:I40) -> 1.2140719e+08 | J41: =SUM(J32:J40) -> 1.93268e+08 | K41: =SUM(K32:K40) -> 3.0962761e+08 | L41: =SUM(L32:L40) -> 5.1013292e+08 | M41: =SUM(M32:M40) -> 8.646637e+08
C43: Investing Activities
C44: Purchase of Property, Plant & Equipment | G44: -7561200 | H44: -31971595 | I44: =-Calculation!I20 -> -43908795 | J44: =-Calculation!J20 -> -64985016 | K44: =-Calculation!K20 -> -99427075 | L44: =-Calculation!L20 -> -1.5709478e+08 | M44: =-Calculation!M20 -> -2.5606449e+08
C45: Net Cash Generated from/(Used) | G45: =SUM(G44) -> -7561200 | H45: =SUM(H44) -> -31971595 | I45: =SUM(I44) -> -43908795 | J45: =SUM(J44) -> -64985016 | K45: =SUM(K44) -> -99427075 | L45: =SUM(L44) -> -1.5709478e+08 | M45: =SUM(M44) -> -2.5606449e+08
C47: Financing Activities
C48: Proceeds from Share Capital | G48: 1000000 | H48: 0 | I48: 0 | J48: 0 | K48: 0 | L48: 0 | M48: 0
C49: Proceeds from Long-Term Loan (Debt) | G49: 0 | H49: 0 | I49: 0 | J49: 0 | K49: 0 | L49: 0 | M49: 0
C50: Repayment of Long-Term Loan (Principal) | G50: 0 | H50: 0 | I50: 0 | J50: 0 | K50: 0 | L50: 0 | M50: 0
C51: Interest Expense | G51: 0 | H51: 0 | I51: 0 | J51: 0 | K51: 0 | L51: 0 | M51: 0
C52: Dividend Payment | G52: 0 | H52: 0 | I52: 0 | J52: 0 | K52: 0 | L52: 0 | M52: 0
C53: Net Cash Generated from/(Used) | G53: =SUM(G48:G52) -> 1000000 | H53: =SUM(H48:H52) -> 0
C55: Net Cash Generated/(Used) During the Year | G55: =G53+G45+G41 -> 313690 | H55: =H53+H45+H41 -> 3707246 | I55: =I53+I45+I41 -> 77498395 | J55: =J53+J45+J41 -> 1.2828299e+08 | K55: =K53+K45+K41 -> 2.1020054e+08 | L55: =L53+L45+L41 -> 3.5303814e+08 | M55: =M53+M45+M41 -> 6.0859921e+08
C56: Cash at the Beginning of the Year | G56: 0 | H56: =G57 -> 313690 | I56: =H57 -> 4020936 | J56: =I57 -> 81519331 | K56: =J57 -> 2.0980232e+08 | L56: =K57 -> 4.2000286e+08 | M56: =L57 -> 7.73041e+08
C57: Cash at the End of the Year | G57: =SUM(G55:G56) -> 313690 | H57: =SUM(H55:H56) -> 4020936 | I57: =SUM(I55:I56) -> 81519331 | J57: =SUM(J55:J56) -> 2.0980232e+08 | K57: =SUM(K55:K56) -> 4.2000286e+08 | L57: =SUM(L55:L56) -> 7.73041e+08 | M57: =SUM(M55:M56) -> 1.3816402e+09
C58: Value in $ | G58: =G57/$C$20 -> 261.40833 | H58: =H57/$C$20 -> 3350.78 | I58: =I57/$C$20 -> 67932.776 | J58: =J57/$C$20 -> 174835.26 | K58: =K57/$C$20 -> 350002.38 | L58: =L57/$C$20 -> 644200.83 | M58: =M57/$C$20 -> 1151366.8
C59: 1200
C62: Statement of financial position
C64: Non-Current Assets
C65: Property, Plant & Equipment | G65: 6859121 | H65: 33194092 | I65: =Calculation!I21 -> 70464068 | J65: =Calculation!J21 -> 1.2135627e+08 | K65: =Calculation!K21 -> 1.9651209e+08 | L65: =Calculation!L21 -> 3.1430445e+08 | M65: =Calculation!M21 -> 5.0750805e+08
C67: Current Assets
C68: Inventory
C69: Receivables | G69: 5689994 | H69: 17542695 | I69: =Calculation!I24 -> 22054646 | J69: =Calculation!J24 -> 32640876 | K69: =Calculation!K24 -> 49940540 | L69: =Calculation!L24 -> 78906053 | M69: =Calculation!M24 -> 1.2861687e+08
C70: Cash | G70: 313691 | H70: 1546060 | I70: =I57 -> 81519331 | J70: =J57 -> 2.0980232e+08 | K70: =K57 -> 4.2000286e+08 | L70: =L57 -> 7.73041e+08 | M70: =M57 -> 1.3816402e+09
C71: Total Current Assets | G71: =SUM(G69:G70) -> 6003685 | H71: =SUM(H69:H70) -> 19088755 | I71: =SUM(I69:I70) -> 1.0357398e+08 | J71: =SUM(J69:J70) -> 2.4244319e+08 | K71: =SUM(K69:K70) -> 4.699434e+08 | L71: =SUM(L69:L70) -> 8.5194705e+08 | M71: =SUM(M69:M70) -> 1.5102571e+09
C73: Total Assets | G73: =G65+G71 -> 12862806 | H73: =H65+H71 -> 52282847 | I73: =I65+I71 -> 1.7403805e+08 | J73: =J65+J71 -> 3.6379946e+08 | K73: =K65+K71 -> 6.6645549e+08 | L73: =L65+L71 -> 1.1662515e+09 | M73: =M65+M71 -> 2.0177651e+09
C74: Value in $ | G74: =G73/$C$20 -> 10719.005 | H74: =H73/$C$20 -> 43569.039 | I74: =I73/$C$20 -> 145031.7 | J74: =J73/$C$20 -> 303166.22 | K74: =K73/$C$20 -> 555379.57 | L74: =L73/$C$20 -> 971876.25 | M74: =M73/$C$20 -> 1681470.9
C75: 1200
C77: Long-Term Liabilities
C78: Long-Term Loan (Debt) | G78: 0 | H78: 0
C80: Current Liabilities
C81: Tax Liabilities | G81: 124 | H81: 0 | I81: =-I40 -> 52116784 | J81: =-J40 -> 79914195 | K81: =-K40 -> 1.2767014e+08 | L81: =-L40 -> 2.1125109e+08 | M81: =-M40 -> 3.6070392e+08
C82: Payables | G82: 9387929 | H82: 12250098 | I82: =Calculation!I25 -> 9924590.6 | J82: =Calculation!J25 -> 13219555 | K82: =Calculation!K25 -> 17978594 | L82: =Calculation!L25 -> 24855407 | M82: =Calculation!M25 -> 34726554
C83: Total Current Liabilities
C85: Total Liabilities | G85: =SUM(G82:G84) -> 9387929 | H85: =SUM(H82:H84) -> 12250098 | I85: =SUM(I82:I84) -> 9924590.6 | J85: =SUM(J82:J84) -> 13219555 | K85: =SUM(K82:K84) -> 17978594 | L85: =SUM(L82:L84) -> 24855407 | M85: =SUM(M82:M84) -> 34726554
C87: Equity
C88: Share Capital | G88: 1000000 | H88: 1000000 | I88: 1000000 | J88: 1000000 | K88: 1000000 | L88: 1000000 | M88: 1000000
C89: Retained Earnings | G89: 2474877 | H89: 39032749 | I89: =I25 -> 1.6311345e+08 | J89: =J25 -> 3.4957991e+08 | K89: =K25 -> 6.4747689e+08 | L89: =L25 -> 1.1403961e+09 | M89: =M25 -> 1.9820386e+09
C90: Total Equity | G90: =SUM(G88:G89) -> 3474877 | H90: =SUM(H88:H89) -> 40032749 | I90: =SUM(I88:I89) -> 1.6411345e+08 | J90: =SUM(J88:J89) -> 3.5057991e+08 | K90: =SUM(K88:K89) -> 6.4847689e+08 | L90: =SUM(L88:L89) -> 1.1413961e+09 | M90: =SUM(M88:M89) -> 1.9830386e+09
C92: Total Equity and Liabilities | G92: =G85+G90 -> 12862806 | H92: =H85+H90 -> 52282847 | I92: =I85+I90 -> 1.7403805e+08 | J92: =J85+J90 -> 3.6379946e+08 | K92: =K85+K90 -> 6.6645549e+08 | L92: =L85+L90 -> 1.1662515e+09 | M92: =M85+M90 -> 2.0177651e+09
C93: Value in $ | G93: =G92/$C$20 -> 10719.005 | H93: =H92/$C$20 -> 43569.039 | I93: =I92/$C$20 -> 145031.7 | J93: =J92/$C$20 -> 303166.22 | K93: =K92/$C$20 -> 555379.57 | L93: =L92/$C$20 -> 971876.25 | M93: =M92/$C$20 -> 1681470.9
C94: 1200
C96: Check | G96: =G73-G92 -> 0 | H96: =H73-H92 -> 0 | I96: =I73-I92 -> 0 | J96: =J73-J92 -> 0 | K96: =K73-K92 -> 0 | L96: =L73-L92 -> 0 | M96: =M73-M92 -> 0

Sheet Calculation
A1: Primary Data mine LTD | G1: 2022 | H1: =G1+1 -> 2023 | I1: =H1+1 -> 2024 | J1: =I1+1 -> 2025 | K1: =J1+1 -> 2026 | L1: =K1+1 -> 2027 | M1: =L1+1 -> 2028
A2: 3-statement financial model | G2: 44562 | H2: 44927 | I2: 45292 | J2: 45658 | K2: 46023 | L2: 46388 | M2: 46753
A3: Figures are in Naira | G3: 44926 | H3: 45291 | I3: 45657 | J3: 46022 | K3: 46387 | L3: 46752 | M3: 47118
C5: Revenue
C6: Growth | G6: =input!G9 -> 0 | H6: =input!H9 -> 0.43 | I6: =input!I9 -> 0.43 | J6: =input!J9 -> 0.48 | K6: =input!K9 -> 0.53 | L6: =input!L9 -> 0.58 | M6: =input!M9 -> 0.63
C8: Cost of goods sold
C9: As a pecentage of Revenue | G9: =input!G12 -> 0 | H9: =input!H12 -> 0.3 | I9: =input!I12 -> 0.3 | J9: =input!J12 -> 0.27 | K9: =input!K12 -> 0.24 | L9: =input!L12 -> 0.21 | M9: =input!M12 -> 0.18
C11: Operating Expenses
C12: As a pecentage of Revenue | G12: =input!G16 -> 0 | H12: =input!H16 -> 0 | I12: =input!I16 -> 0.02 | J12: =input!J16 -> 0.025 | K12: =input!K16 -> 0.03 | L12: =input!L16 -> 0.035 | M12: =input!M16 -> 0.04
C14: Personnel Expenses
C15: As a pecentage of Revenue | G15: =input!G20 -> -0.41662983 | H15: =input!H20 -> -0.18708345 | I15: =input!I20 -> -0.18708345 | J15: =input!J20 -> -0.18708345 | K15: =input!K20 -> -0.18708345 | L15: =input!L20 -> -0.18708345 | M15: =input!M20 -> -0.18708345
C17: PPE Schedule
C18: Opening balance | I18: =H21 -> 33194092 | J18: =I21 -> 70464068 | K18: =J21 -> 1.2135627e+08 | L18: =K21 -> 1.9651209e+08 | M18: =L21 -> 3.1430445e+08
C19: Depreciation | I19: =-input!$H$27*Calculation!I18 -> -6638818.4 | J19: =-input!$H$27*Calculation!J18 -> -14092814 | K19: =-input!$H$27*Calculation!K18 -> -24271254 | L19: =-input!$H$27*Calculation!L18 -> -39302418 | M19: =-input!$H$27*Calculation!M18 -> -62860890
C20: Addition | I20: =input!$G$30*Output!I5 -> 43908795 | J20: =input!$G$30*Output!J5 -> 64985016 | K20: =input!$G$30*Output!K5 -> 99427075 | L20: =input!$G$30*Output!L5 -> 1.5709478e+08 | M20: =input!$G$30*Output!M5 -> 2.5606449e+08
C21: Closing balance | H21: =Output!H65 -> 33194092 | I21: =SUM(I18:I20) -> 70464068 | J21: =SUM(J18:J20) -> 1.2135627e+08 | K21: =SUM(K18:K20) -> 1.9651209e+08 | L21: =SUM(L18:L20) -> 3.1430445e+08 | M21: =SUM(M18:M20) -> 5.0750805e+08
C23: Working Capital
C24: Receivables | G24: =input!G33/input!$G$5*Output!G5 -> 5689994 | H24: =input!H33/input!$G$5*Output!H5 -> 17542695 | I24: =input!I33/input!$G$5*Output!I5 -> 22054646 | J24: =input!J33/input!$G$5*Output!J5 -> 32640876 | K24: =input!K33/input!$G$5*Output!K5 -> 49940540 | L24: =input!L33/input!$G$5*Output!L5 -> 78906053 | M24: =input!M33/input!$G$5*Output!M5 -> 1.2861687e+08
C25: Payables | G25: =input!G34/input!$G$5*-Output!G6 -> 9387929 | H25: =input!H34/input!$G$5*-Output!H6 -> 12250098 | I25: =input!I34/input!$G$5*-Output!I6 -> 9924590.6 | J25: =input!J34/input!$G$5*-Output!J6 -> 13219555 | K25: =input!K34/input!$G$5*-Output!K6 -> 17978594 | L25: =input!L34/input!$G$5*-Output!L6 -> 24855407 | M25: =input!M34/input!$G$5*-Output!M6 -> 34726554
C27: Changes in working Capital | G27: =(F24-G24)+(G25-F25) -> 3697935 | H27: =(G24-H24)+(H25-G25) -> -8990532 | I27: =(H24-I24)+(I25-H25) -> -6837458.2 | J27: =(I24-J24)+(J25-I25) -> -7291265.9 | K27: =(J24-K24)+(K25-J25) -> -12540624 | L27: =(K24-L24)+(L25-K25) -> -22088701 | M27: =(L24-M24)+(M25-L25) -> -39839666

Sheet input
A1: Primary Data mine LTD | G1: 2022 | H1: =G1+1 -> 2023 | I1: =H1+1 -> 2024 | J1: =I1+1 -> 2025 | K1: =J1+1 -> 2026 | L1: =K1+1 -> 2027 | M1: =L1+1 -> 2028
A2: 3-statement financial model | G2: 44562 | H2: 44927 | I2: 45292 | J2: 45658 | K2: 46023 | L2: 46388 | M2: 46753
A3: Figures are in Naira | G3: 44926 | H3: 45291 | I3: 45657 | J3: 46022 | K3: 46387 | L3: 46752 | M3: 47118
C4: General assumptions
C5: Days | G5: 365
C6: Months | G6: 12
C8: Revenue
C9: growth in Revenue | G9: 0 | H9: 0.43 | I9: 0.43 | J9: =I9+5% -> 0.48 | K9: =J9+5% -> 0.53 | L9: =K9+5% -> 0.58 | M9: =L9+5% -> 0.63
C11: Cost of goods sold
C12: Cost of goods as % of revenue | G12: 0 | H12: =30% -> 0.3 | I12: 0.3 | J12: =I12-3% -> 0.27 | K12: =J12-3% -> 0.24 | L12: =K12-3% -> 0.21 | M12: =L12-3% -> 0.18
C15: Operating Expenses
C16: Operating Expenses as % of revenue | I16: =2% -> 0.02 | J16: =I16+0.5% -> 0.025 | K16: =J16+0.5% -> 0.03 | L16: =K16+0.5% -> 0.035 | M16: =L16+0.5% -> 0.04
C19: Personel Expenses
C20: as a pecentage of revenue | G20: =Output!G10/Output!G5 -> -0.41662983 | H20: =Output!H10/Output!H5 -> -0.18708345 | I20: =H20 -> -0.18708345 | J20: =I20 -> -0.18708345 | K20: =J20 -> -0.18708345 | L20: =K20 -> -0.18708345 | M20: =L20 -> -0.18708345
C22: Taxation
C23: CIT | G23: 0.3
C25: Depreciation
G26: Years
C27: Furniture and Fittings | G27: 5 | H27: 0.2
C28: Office equipment | G28: 5 | H28: 0.2
C29: Computer equipment | G29: 5 | H29: 0.2
C30: additions as a pecentage of revenue | G30: =12% -> 0.12
C32: Working Capital Days
C33: Receivables | G33: =(Output!G69/Output!G5)*$G$5 -> 90.749629 | H33: =(Output!H69/Output!H5)*365 -> 25.023897 | I33: 22 | J33: 22 | K33: 22 | L33: 22 | M33: 22
C34: Payables | G34: =(Output!G82/-Output!G6)*input!$G$5 -> 410.24276 | H34: =(Output!H82/-Output!H6)*input!$G$5 -> 30.046115 | I34: 33 | J34: 33 | K34: 33 | L34: 33 | M34: 33
